README.txt
setup.cfg
setup.py
collective/__init__.py
collective.checkpermission.egg-info/PKG-INFO
collective.checkpermission.egg-info/SOURCES.txt
collective.checkpermission.egg-info/dependency_links.txt
collective.checkpermission.egg-info/entry_points.txt
collective.checkpermission.egg-info/namespace_packages.txt
collective.checkpermission.egg-info/not-zip-safe
collective.checkpermission.egg-info/paster_plugins.txt
collective.checkpermission.egg-info/requires.txt
collective.checkpermission.egg-info/top_level.txt
collective/checkpermission/README.txt
collective/checkpermission/__init__.py
collective/checkpermission/check.py
collective/checkpermission/check.txt
collective/checkpermission/configure.zcml
collective/checkpermission/interfaces.py
collective/checkpermission/tests/__init__.py
collective/checkpermission/tests/base.py
collective/checkpermission/tests/test_check.py
collective/checkpermission/tests/test_doctest.py
docs/HISTORY.txt
docs/INSTALL.txt
docs/LICENSE.GPL
docs/LICENSE.txt