Metadata-Version: 1.0
Name: collective.checkpermission
Version: 1.0
Summary: Provides a decorator for protect methods of browser views
Home-page: http://redomino.com
Author: Davide Moro
Author-email: davide.moro@redomino.com
License: GPL
Keywords: plone
Platform: UNKNOWN
Classifier: Framework :: Plone
Classifier: Programming Language :: Python
